theohe_functions/__init__.py
theohe_functions/export/__init__.py
theohe_functions/export/excel_file.py
theohe_functions/plotting/__init__.py
theohe_functions/plotting/candlestick.py
theohe_functions/stock/__init__.py
theohe_functions/stock/analysis/__init__.py
theohe_functions/stock/analysis/functions.py
theohe_functions/stock/data/__init__.py
theohe_functions/stock/data/download.py
theohe_functions/timeframe/__init__.py
theohe_functions/timeframe/call_time.py
theohe_functions/timeframe/get_frame.py
theohe_functions-0.0.1.dist-info/LICENSE
theohe_functions-0.0.1.dist-info/METADATA
theohe_functions-0.0.1.dist-info/WHEEL
theohe_functions-0.0.1.dist-info/top_level.txt
theohe_functions-0.0.1.dist-info/RECORD
